ravest/__init__.py
ravest/fit.py
ravest/model.py
ravest/param.py
ravest/prior.py
ravest-0.2.5.dist-info/LICENSE
ravest-0.2.5.dist-info/METADATA
ravest-0.2.5.dist-info/WHEEL
ravest-0.2.5.dist-info/RECORD
