Metadata-Version: 2.3
Name: ravest
Version: 0.2.5
Summary: Radial Velocity fitting, simulation and model comparison
License: MIT
Author: Ross Dobson
Author-email: 56548895+ross-dobson@users.noreply.github.com
Requires-Python: >=3.11
Classifier: Development Status :: 2 - Pre-Alpha
Classifier: Programming Language :: Python :: 3
Classifier: Operating System :: OS Independent
Classifier: Intended Audience :: Science/Research
Classifier: Natural Language :: English
Classifier: Topic :: Scientific/Engineering :: Astronomy
Requires-Dist: astropy (>=7.1.0,<8.0.0)
Requires-Dist: corner (>=2.2.3,<3.0.0)
Requires-Dist: emcee (>=3.1.6,<4.0.0)
Requires-Dist: harmonic (>=1.3.0,<2.0.0)
Requires-Dist: jax (<0.6)
Requires-Dist: matplotlib (>=3.10.3,<4.0.0)
Requires-Dist: numpy (<2)
Requires-Dist: pandas (>=2.3.0,<3.0.0)
Requires-Dist: scipy (>=1.16.0,<2.0.0)
Requires-Dist: tinygp (>=0.3.0,<0.4.0)
Requires-Dist: tqdm (>=4.67.1,<5.0.0)
Project-URL: Homepage, https://ravest.readthedocs.io
Project-URL: Repository, https://www.github.com/ross-dobson/ravest
